eindex/__init__.py
eindex/_parsing.py
eindex/_utils.py
eindex/indexing.py
eindex_callum-0.1.2.dist-info/METADATA
eindex_callum-0.1.2.dist-info/WHEEL
eindex_callum-0.1.2.dist-info/top_level.txt
eindex_callum-0.1.2.dist-info/RECORD
