Metadata-Version: 2.1
Name: eindex-callum
Version: 0.1.2
Summary: My interpretation of einops-like indexing
Home-page: https://github.com/callummcdougall/eindex
Author: Callum McDougall
Author-email: cal.s.mcdougall@gmail.com
Classifier: Programming Language :: Python :: 3
Classifier: Operating System :: OS Independent
Requires-Dist: torch
Requires-Dist: einops
